pymembercli/__init__.py
pymembercli/__main__.py
pymembercli/cmds.py
pymembercli/pymember.py
pymembercli/task_item.py
pymembercli-0.4.6.dist-info/METADATA
pymembercli-0.4.6.dist-info/WHEEL
pymembercli-0.4.6.dist-info/entry_points.txt
pymembercli-0.4.6.dist-info/RECORD
