Metadata-Version: 2.1
Name: pymembercli
Version: 0.4.6
Summary: 
Author: lawnchairmeku
Author-email: mekumotoki@gmail.com
Requires-Python: >=3.12,<4.0
Classifier: Programming Language :: Python :: 3
Classifier: Programming Language :: Python :: 3.12
Requires-Dist: platformdirs (>=4.3.6,<5.0.0)
Requires-Dist: pympmyansi (>=0.2.0,<0.3.0)
